mirus_django_csv.py
mirus_django_csv-1.1.0.dist-info/DESCRIPTION.rst
mirus_django_csv-1.1.0.dist-info/METADATA
mirus_django_csv-1.1.0.dist-info/RECORD
mirus_django_csv-1.1.0.dist-info/WHEEL
mirus_django_csv-1.1.0.dist-info/metadata.json
mirus_django_csv-1.1.0.dist-info/top_level.txt
