Metadata-Version: 2.0
Name: mirus-django-csv
Version: 1.1.0
Summary: Takes a django queryset, or a list, or a generator and creates a csv from it
Home-page: https://github.com/mirusresearch/mirus_django_csv
Author: Mirus Research
Author-email: frank@mirusresearch.com
License: MIT license, see LICENSE
Platform: UNKNOWN
Requires-Dist: six (>=1.11.0)
